[
  {
    "id": 1,
    "title": "NTV",
    "address": "XEJM4Hcgd3M",
    "isSelected": true,
    "autoplay": false
  },
  {
    "id": 2,
    "title": "HABERTÜRK",
    "address": "SqHIO2zhxbA",
    "isSelected": true,
    "autoplay": false
  },
  {
    "id": 3,
    "title": "HABER GLOBAL",
    "address": "UVPejgEw21c",
    "isSelected": true,
    "autoplay": false
  },
  {
    "id": 4,
    "title": "TRT HABER",
    "address": "-Lrxv1_i3qc",
    "isSelected": true,
    "autoplay": false
  },
  {
    "id": 5,
    "title": "TV 100",
    "address": "sd94keSra6A",
    "isSelected": false,
    "autoplay": false
  },
  {
    "id": 6,
    "title": "HALK TV",
    "address": "r2ZgRoX2orE",
    "isSelected": false,
    "autoplay": false
  },
  {
    "id": 7,
    "title": "TGRT HABER",
    "address": "gzmG_1SVy8Y",
    "isSelected": false,
    "autoplay": false
  },
  {
    "id": 8,
    "title": "KRT TV",
    "address": "3QDiWPZ2D_k",
    "isSelected": false,
    "autoplay": false
  },
  {
    "id": 9,
    "title": "TELE1 ",
    "address": "eenp_e9_c1Q",
    "isSelected": false,
    "autoplay": false
  },
  {
    "id": 10,
    "title": "SÖZCÜ TV",
    "address": "1amrc2Mxjhs",
    "isSelected": false,
    "autoplay": false
  },
  {
    "id": 11,
    "title": "ARTI TV",
    "address": "xpoetRCJKqY",
    "isSelected": false,
    "autoplay": false
  },
  {
    "id": 12,
    "title": "ULUSAL KANAL",
    "address": "LRzXIpwR2Eo",
    "isSelected": false,
    "autoplay": false
  },
  {
    "id": 13,
    "title": "BLOOMBERG HT",
    "address": "hHSmBJk6w0c",
    "isSelected": false,
    "autoplay": false
  },
  {
    "id": 14,
    "title": "TVNET",
    "address": "UVW4-DQUVUU",
    "isSelected": false,
    "autoplay": false
  },
  {
    "id": 15,
    "title": "FLASH HABER TV",
    "address": "oGHfM6AC7QU",
    "isSelected": false,
    "autoplay": false
  },
  {
    "id": 16,
    "title": "BENGÜTÜRK TV",
    "address": "GKwLomZwX_k",
    "isSelected": false,
    "autoplay": false
  },
  {
    "id": 17,
    "title": "TV5",
    "address": "zNkYBJ0wKI",
    "isSelected": false,
    "autoplay": false
  },
  {
    "id": 18,
    "title": "EKOTÜRK TV",
    "address": "oeFbaX4qqxc",
    "isSelected": false,
    "autoplay": false
  }
]